pynepsys
