Metadata-Version: 2.1
Name: pynepsys
Version: 1.2.1
Summary: Python library for Neptune Systems Apex
Home-page: https://github.com/jpelzer/pynepsys
Author: Jason Pelzer
Author-email: pypi.org@pelzer.com
License: MIT
Platform: UNKNOWN
Classifier: License :: OSI Approved :: MIT License
Classifier: Programming Language :: Python :: 3
Classifier: Programming Language :: Python :: 3.7
